TME4_VHDL_ALUfinal_shifter/alu.vhdl
library IEEE;
use IEEE.std_logic_1164.all;
use IEEE.numeric_std.all;

entity Alu is

    port (
            op1  : in  std_logic_vector(31 downto 0);
            op2  : in  std_logic_vector(31 downto 0);
            cin  : in  std_logic_vector(0 downto 0);
            cmd  : in  std_logic_vector(1 downto 0);
            res  : out std_logic_vector(31 downto 0);
            cout : out std_logic;
            z    : out std_logic;
            n    : out std_logic;
            v    : out std_logic;
            vdd  : in  bit;
            vss  : in  bit );

end Alu;

architecture alu_archi of Alu is
signal tmp2 : std_logic_vector(0 downto 0);
begin

process (cmd,op1,op2)
variable tmp : std_logic_vector(32 downto 0):="000000000000000000000000000000000";

begin
case cmd is

when "00" =>
tmp := std_logic_vector('0'&unsigned(op1)+unsigned(op2)+unsigned(cin));
cout <= tmp(32);
res <= tmp(31 downto 0);

when "01" =>
res <= op1 AND op2;

when "10" =>
res <= op1 OR op2;

when "11" =>
res <= op1 XOR op2;

when others =>
res <= tmp(31 downto 0);
end case;


if tmp = "000000000000000000000000000000000" then
z <= '1';
else
z <= '0';
end if;

if tmp(31) = '1' then
n <= '1';
else
n <= '0';
end if;


tmp2 <= op1(31 downto 31) XOR op2(31 downto 31);

if (tmp2 = "0") AND ((tmp(31 downto 31) /= (op1(31 downto 31))))  then
v <= '1';
else
v <= '0';
end if;

end process;
end architecture;

TME4_VHDL_ALUfinal_shifter/alu.vcd
$date
  Wed Oct 18 11:14:54 2023
$end
$version
  GHDL v0
$end
$timescale
  1 fs
$end
$var reg 32 ! op1[31:0] $end
$var reg 32 " op2[31:0] $end
$var reg 32 # res[31:0] $end
$var reg 1 $ cin[0:0] $end
$var reg 2 % cmd[1:0] $end
$var reg 1 & cout $end
$var reg 1 ' z $end
$var reg 1 ( n $end
$var reg 1 ) v $end
$var reg 1 * vdd $end
$var reg 1 + vss $end
$scope module alu $end
$var reg 32 , op1[31:0] $end
$var reg 32 - op2[31:0] $end
$var reg 1 . cin[0:0] $end
$var reg 2 / cmd[1:0] $end
$var reg 32 0 res[31:0] $end
$var reg 1 1 cout $end
$var reg 1 2 z $end
$var reg 1 3 n $end
$var reg 1 4 v $end
$var reg 1 5 vdd $end
$var reg 1 6 vss $end
$var reg 1 7 tmp2[0:0] $end
$upscope $end
$enddefinitions $end
#0
b00000000000000000000000000000000 !
b00000000000000000000000000000000 "
b00000000000000000000000000000000 #
b0 $
b00 %
0&
1'
0(
0)
0*
0+
b00000000000000000000000000000000 ,
b00000000000000000000000000000000 -
b0 .
b00 /
b00000000000000000000000000000000 0
01
12
03
04
05
06
b0 7
#100000000
b10101010101010101010101010101010 !
b10101010101010101010101010101010 #
0'
1(
b10101010101010101010101010101010 ,
b10101010101010101010101010101010 0
02
13
b1 7
#150000000
b10001000100010001000100010001000 "
b00110011001100110011001100110010 #
1&
0(
b10001000100010001000100010001000 -
b00110011001100110011001100110010 0
11
03
b0 7
#200000000
b01111111111111111111111111111111 !
b01111111111111111111111111111111 "
b11111111111111111111111111111110 #
0&
1(
1)
b01111111111111111111111111111111 ,
b01111111111111111111111111111111 -
b11111111111111111111111111111110 0
01
13
14
#300000000
b00000000000000000000000000000000 !
b00000000000000000000000000000010 "
b00000000000000000000000000000000 #
b01 %
b00000000000000000000000000000000 ,
b00000000000000000000000000000010 -
b01 /
b00000000000000000000000000000000 0
#400000000
b00000000000000000000000000000010 !
b00000000000000000000000000000010 #
b00000000000000000000000000000010 ,
b00000000000000000000000000000010 0
#500000000
b00000000000000000000000000000000 "
b10 %
b00000000000000000000000000000000 -
b10 /
#600000000
b00000000000000000000000000000000 !
b00000000000000000000000000000010 "
b00000000000000000000000000000000 ,
b00000000000000000000000000000010 -
#700000000
b00000000000000000000000000000010 !
b00000000000000000000000000000000 #
b11 %
b00000000000000000000000000000010 ,
b11 /
b00000000000000000000000000000000 0
#800000000
b00000000000000000000000000000001 !
b00000000000000000000000000000011 #
b00000000000000000000000000000001 ,
b00000000000000000000000000000011 0
#2000000000
b11111111111111111111111111111111 "
b11111111111111111111111111111110 #
b11111111111111111111111111111111 -
b11111111111111111111111111111110 0
b1 7
